astmareq1/__init__.py
astmareq1-1.0.dist-info/METADATA
astmareq1-1.0.dist-info/WHEEL
astmareq1-1.0.dist-info/top_level.txt
astmareq1-1.0.dist-info/RECORD
